pystatemachine/__init__.py
pystatemachine/manager.py
simple_gamestates-2.dist-info/licenses/LICENSE
simple_gamestates-2.dist-info/METADATA
simple_gamestates-2.dist-info/WHEEL
simple_gamestates-2.dist-info/top_level.txt
simple_gamestates-2.dist-info/RECORD
