Metadata-Version: 2.4
Name: simple-gamestates
Version: 2
Summary: A simple and abstract state machine manager for Python game development.
Home-page: https://github.com/pozi-dev/simple-gamestates
Author: Pozi
Author-email: pozi@logicbyte.org
License: MIT License
Classifier: Programming Language :: Python :: 3
Classifier: License :: OSI Approved :: MIT License
Classifier: Operating System :: OS Independent
Classifier: Development Status :: 3 - Alpha
Classifier: Intended Audience :: Developers
Classifier: Topic :: Software Development :: Libraries :: Python Modules
Classifier: Topic :: Games/Entertainment
Requires-Python: >=3.7
License-File: LICENSE
Dynamic: license-file
